AUTHORS
CHANGELOG.txt
DESCRIPTION
LICENSE
MANIFEST.in
README.rst
setup.py
django_oscar_sagepay.egg-info/PKG-INFO
django_oscar_sagepay.egg-info/SOURCES.txt
django_oscar_sagepay.egg-info/dependency_links.txt
django_oscar_sagepay.egg-info/requires.txt
django_oscar_sagepay.egg-info/top_level.txt
sagepay/.DS_Store
sagepay/__init__.py
sagepay/facade.py
sagepay/forms.py
sagepay/gateway.py
sagepay/models.py
sagepay/tests.py
sagepay/utils.py
sagepay/views.py
sandbox/__init__.py
sandbox/manage.py
sandbox/settings.py
sandbox/urls.py
sandbox/apps/__init__.py