Metadata-Version: 1.1
Name: django-oscar-sagepay
Version: 0.0.3
Summary: This package provides integration between django-oscar and the payment gateway SagePay UK
